flaskbb_plugin_vanity-0.1.0.dist-info/METADATA
flaskbb_plugin_vanity-0.1.0.dist-info/RECORD
flaskbb_plugin_vanity-0.1.0.dist-info/WHEEL
flaskbb_plugin_vanity-0.1.0.dist-info/entry_points.txt
flaskbb_plugin_vanity-0.1.0.dist-info/top_level.txt
vanity/__init__.py
vanity/models.py
vanity/views.py
vanity/migrations/201807261925_96daae59325b_like_functionality.py
vanity/migrations/201808201955_dd4a44376f72_a_couple_constraints_for_the_.py
vanity/templates/liked_posts.html
vanity/templates/vanity_like_button.html
