Metadata-Version: 2.1
Name: flaskbb-plugin-vanity
Version: 0.1.0
Summary: Like functionality for flaskBB.
Home-page: UNKNOWN
Author: Михаил Лебедев
Author-email: micha030201@gmail.com
License: BSD License
Keywords: flaskbb plugin
Platform: any
Classifier: Development Status :: 3 - Alpha
Classifier: Environment :: Web Environment
Classifier: Environment :: Plugins
Classifier: Framework :: Flask
Classifier: Intended Audience :: Developers
Classifier: License :: OSI Approved :: BSD License
Classifier: Operating System :: OS Independent
Classifier: Programming Language :: Python
Classifier: Programming Language :: Python :: 3
Classifier: Topic :: Internet :: WWW/HTTP :: Dynamic Content
Classifier: Topic :: Software Development :: Libraries :: Python Modules
Requires-Dist: FlaskBB
